MANIFEST.in
README.rst
setup.py
compliancelib/__init__.py
compliancelib/assessor.py
compliancelib/nist800_53.py
compliancelib/nist800_53viz.py
compliancelib/opencontrolfiles.py
compliancelib/systemcompliance.py
compliancelib.egg-info/PKG-INFO
compliancelib.egg-info/SOURCES.txt
compliancelib.egg-info/dependency_links.txt
compliancelib.egg-info/not-zip-safe
compliancelib.egg-info/requires.txt
compliancelib.egg-info/top_level.txt
compliancelib/data/800-53-controls.2014-07-29.xml
compliancelib/data/800-53-controls.2015-02-03.xml
compliancelib/data/800-53-controls.xml
compliancelib/data/800-53a-objectives.xml
compliancelib/data/AU_policy_component.yaml
compliancelib/data/NIST.SP.800-53Ar4.pdf
compliancelib/data/NIST.SP.800-53r4.pdf
compliancelib/data/UAA_component.yaml
compliancelib/data/dependencies/AC-.txt
compliancelib/data/dependencies/AT-.txt
compliancelib/data/dependencies/AU-.txt
compliancelib/data/dependencies/CA-.txt
compliancelib/data/dependencies/CM-.txt
compliancelib/data/dependencies/CP-.txt
compliancelib/data/dependencies/IA-.txt
compliancelib/data/dependencies/IR-.txt
compliancelib/data/dependencies/MA-.txt
compliancelib/data/dependencies/MP-.txt
compliancelib/data/dependencies/PE-.txt
compliancelib/data/dependencies/PL-.txt
compliancelib/data/dependencies/PM-.txt
compliancelib/data/dependencies/PS-.txt
compliancelib/data/dependencies/RA-.txt
compliancelib/data/dependencies/SA-.txt
compliancelib/data/dependencies/SE-.txt
compliancelib/data/dependencies/SI-.txt