Metadata-Version: 1.1
Name: compliancelib
Version: 1.1.2
Summary: A python library for modeling IT Compliance
Home-page: http://github.com/govready/compliancelib-python
Author: Greg Elin
Author-email: gregelin@govready.com
License: GNU General Public License v3 (GPLv3)
Keywords: compliance FISMA DICAP PCI
Platform: UNKNOWN
Classifier: Development Status :: 4 - Beta
Classifier: License :: OSI Approved :: GNU General Public License v3 (GPLv3)
Classifier: Programming Language :: Python :: 3.0
Classifier: Operating System :: MacOS
Classifier: Operating System :: Unix
Classifier: Programming Language :: Python
Classifier: Programming Language :: Python :: 2.7
Classifier: Programming Language :: Python :: 3
Classifier: Topic :: Software Development :: Libraries :: Python Modules
Classifier: Topic :: Software Development :: Documentation
